{
  "version": 1,
  "generated_at": "2026-02-13T20:49:26+09:00",
  "tags": [
    {
      "tag_id": "attr_guerrilla",
      "label": "ゲリラ",
      "group": "attr",
      "is_active": true
    },
    {
      "tag_id": "format_chat",
      "label": "雑談系",
      "group": "format",
      "is_active": true
    },
    {
      "tag_id": "format_drawing",
      "label": "お絵描き系",
      "group": "format",
      "is_active": true
    },
    {
      "tag_id": "format_event",
      "label": "イベント系",
      "group": "format",
      "is_active": true
    },
    {
      "tag_id": "format_game",
      "label": "ゲーム系",
      "group": "format",
      "is_active": true
    },
    {
      "tag_id": "format_short",
      "label": "ショート",
      "group": "format",
      "is_active": true
    },
    {
      "tag_id": "format_sing",
      "label": "歌枠",
      "group": "format",
      "is_active": true
    },
    {
      "tag_id": "format_watchalong",
      "label": "同時視聴系",
      "group": "format",
      "is_active": true
    },
    {
      "tag_id": "motif_04405b5a7e",
      "label": "完全初見",
      "group": "motif",
      "is_active": true
    },
    {
      "tag_id": "motif_0c3d461581",
      "label": "人生初",
      "group": "motif",
      "is_active": true
    },
    {
      "tag_id": "motif_10ea0afcc8",
      "label": "バイト",
      "group": "motif",
      "is_active": true
    },
    {
      "tag_id": "motif_1462271471",
      "label": "アナリティクス",
      "group": "motif",
      "is_active": true
    },
    {
      "tag_id": "motif_1ab83377b5",
      "label": "今週",
      "group": "motif",
      "is_active": true
    },
    {
      "tag_id": "motif_1d9246f3bd",
      "label": "テンション",
      "group": "motif",
      "is_active": true
    },
    {
      "tag_id": "motif_2061310567",
      "label": "マシュマロ",
      "group": "motif",
      "is_active": true
    },
    {
      "tag_id": "motif_20dcba7989",
      "label": "相談",
      "group": "motif",
      "is_active": true
    },
    {
      "tag_id": "motif_25486ad4e5",
      "label": "問題",
      "group": "motif",
      "is_active": true
    },
    {
      "tag_id": "motif_2bd84df574",
      "label": "深夜",
      "group": "motif",
      "is_active": true
    },
    {
      "tag_id": "motif_2c718f4d9c",
      "label": "記憶",
      "group": "motif",
      "is_active": true
    },
    {
      "tag_id": "motif_3068a66b20",
      "label": "余裕",
      "group": "motif",
      "is_active": true
    },
    {
      "tag_id": "motif_32a711d933",
      "label": "実写",
      "group": "motif",
      "is_active": true
    },
    {
      "tag_id": "motif_35376ffb91",
      "label": "マッマ",
      "group": "motif",
      "is_active": true
    },
    {
      "tag_id": "motif_35a9a05524",
      "label": "作業雑談",
      "group": "motif",
      "is_active": true
    },
    {
      "tag_id": "motif_36bb53c563",
      "label": "準備中",
      "group": "motif",
      "is_active": true
    },
    {
      "tag_id": "motif_37ce9d5f47",
      "label": "歌枠",
      "group": "motif",
      "is_active": true
    },
    {
      "tag_id": "motif_3817a0e701",
      "label": "漢字",
      "group": "motif",
      "is_active": true
    },
    {
      "tag_id": "motif_3e747c4b9f",
      "label": "愚痴",
      "group": "motif",
      "is_active": true
    },
    {
      "tag_id": "motif_42884ef8fc",
      "label": "途中",
      "group": "motif",
      "is_active": true
    },
    {
      "tag_id": "motif_473d9fea10",
      "label": "披露",
      "group": "motif",
      "is_active": true
    },
    {
      "tag_id": "motif_47fa49e26f",
      "label": "スイカゲーム",
      "group": "motif",
      "is_active": true
    },
    {
      "tag_id": "motif_48e8fd209c",
      "label": "絵描",
      "group": "motif",
      "is_active": true
    },
    {
      "tag_id": "motif_4c85c23407",
      "label": "サムネ",
      "group": "motif",
      "is_active": true
    },
    {
      "tag_id": "motif_5312d71158",
      "label": "案件",
      "group": "motif",
      "is_active": true
    },
    {
      "tag_id": "motif_55a4aba8bc",
      "label": "グッズ",
      "group": "motif",
      "is_active": true
    },
    {
      "tag_id": "motif_55c42ca308",
      "label": "妄想",
      "group": "motif",
      "is_active": true
    },
    {
      "tag_id": "motif_55d4da46c6",
      "label": "作業",
      "group": "motif",
      "is_active": true
    },
    {
      "tag_id": "motif_55fac25c11",
      "label": "3d",
      "group": "motif",
      "is_active": true
    },
    {
      "tag_id": "motif_69a71edee6",
      "label": "作業配信",
      "group": "motif",
      "is_active": true
    },
    {
      "tag_id": "motif_6b8a692d61",
      "label": "寝坊",
      "group": "motif",
      "is_active": true
    },
    {
      "tag_id": "motif_703beb06b9",
      "label": "文化祭",
      "group": "motif",
      "is_active": true
    },
    {
      "tag_id": "motif_7528a81092",
      "label": "青春",
      "group": "motif",
      "is_active": true
    },
    {
      "tag_id": "motif_8221220aeb",
      "label": "カオス",
      "group": "motif",
      "is_active": true
    },
    {
      "tag_id": "motif_8bac69cf5a",
      "label": "アンダーテール",
      "group": "motif",
      "is_active": true
    },
    {
      "tag_id": "motif_8bf891a2d6",
      "label": "チャレンジ",
      "group": "motif",
      "is_active": true
    },
    {
      "tag_id": "motif_8d3cf88ed2",
      "label": "梱包",
      "group": "motif",
      "is_active": true
    },
    {
      "tag_id": "motif_8ef5c205a5",
      "label": "ビーンズ",
      "group": "motif",
      "is_active": true
    },
    {
      "tag_id": "motif_9514e8de7a",
      "label": "交錯",
      "group": "motif",
      "is_active": true
    },
    {
      "tag_id": "motif_95f825cc41",
      "label": "談義",
      "group": "motif",
      "is_active": true
    },
    {
      "tag_id": "motif_994153c00f",
      "label": "ホラー",
      "group": "motif",
      "is_active": true
    },
    {
      "tag_id": "motif_9c1ff0bdc2",
      "label": "オタク",
      "group": "motif",
      "is_active": true
    },
    {
      "tag_id": "motif_a1d1ec67e3",
      "label": "個人",
      "group": "motif",
      "is_active": true
    },
    {
      "tag_id": "motif_a5db5553d6",
      "label": "幼少期",
      "group": "motif",
      "is_active": true
    },
    {
      "tag_id": "motif_a789cd2f1c",
      "label": "連打",
      "group": "motif",
      "is_active": true
    },
    {
      "tag_id": "motif_asmr",
      "label": "asmr",
      "group": "motif",
      "is_active": true
    },
    {
      "tag_id": "motif_b0f1c5a480",
      "label": "テスト",
      "group": "motif",
      "is_active": true
    },
    {
      "tag_id": "motif_b5f2e16411",
      "label": "部屋",
      "group": "motif",
      "is_active": true
    },
    {
      "tag_id": "motif_b7b486ac27",
      "label": "告知",
      "group": "motif",
      "is_active": true
    },
    {
      "tag_id": "motif_ba48385145",
      "label": "同時視聴",
      "group": "motif",
      "is_active": true
    },
    {
      "tag_id": "motif_c086b3008a",
      "label": "世界",
      "group": "motif",
      "is_active": true
    },
    {
      "tag_id": "motif_c0af3a1264",
      "label": "アニメ",
      "group": "motif",
      "is_active": true
    },
    {
      "tag_id": "motif_cb1f7d20a4",
      "label": "家族",
      "group": "motif",
      "is_active": true
    },
    {
      "tag_id": "motif_cb3b9578bb",
      "label": "ゲリラ",
      "group": "motif",
      "is_active": true
    },
    {
      "tag_id": "motif_cfc767a667",
      "label": "仕事",
      "group": "motif",
      "is_active": true
    },
    {
      "tag_id": "motif_d1bc50c34a",
      "label": "脱線",
      "group": "motif",
      "is_active": true
    },
    {
      "tag_id": "motif_dae29909a7",
      "label": "性癖",
      "group": "motif",
      "is_active": true
    },
    {
      "tag_id": "motif_dc07c9bb88",
      "label": "職場",
      "group": "motif",
      "is_active": true
    },
    {
      "tag_id": "motif_ddbab2663e",
      "label": "朝活",
      "group": "motif",
      "is_active": true
    },
    {
      "tag_id": "motif_deba64e8e6",
      "label": "クリア",
      "group": "motif",
      "is_active": true
    },
    {
      "tag_id": "motif_e79ab791c2",
      "label": "スパチャ",
      "group": "motif",
      "is_active": true
    },
    {
      "tag_id": "motif_e9f1c5310a",
      "label": "個人勢",
      "group": "motif",
      "is_active": true
    },
    {
      "tag_id": "motif_ed39f966e6",
      "label": "ツッコミ",
      "group": "motif",
      "is_active": true
    },
    {
      "tag_id": "motif_f4e0cc019d",
      "label": "イラスト",
      "group": "motif",
      "is_active": true
    },
    {
      "tag_id": "motif_f6ee8cbf7f",
      "label": "初配信",
      "group": "motif",
      "is_active": true
    },
    {
      "tag_id": "motif_f93c54682f",
      "label": "目指",
      "group": "motif",
      "is_active": true
    },
    {
      "tag_id": "motif_f9f7bb6679",
      "label": "文化",
      "group": "motif",
      "is_active": true
    },
    {
      "tag_id": "motif_fc15322dcc",
      "label": "トラブル",
      "group": "motif",
      "is_active": true
    },
    {
      "tag_id": "motif_line",
      "label": "line",
      "group": "motif",
      "is_active": true
    },
    {
      "tag_id": "motif_live2d",
      "label": "live2d",
      "group": "motif",
      "is_active": true
    },
    {
      "tag_id": "motif_pon",
      "label": "pon",
      "group": "motif",
      "is_active": true
    },
    {
      "tag_id": "motif_rpg",
      "label": "rpg",
      "group": "motif",
      "is_active": true
    },
    {
      "tag_id": "motif_sandtrix",
      "label": "sandtrix+",
      "group": "motif",
      "is_active": true
    },
    {
      "tag_id": "motif_simulator",
      "label": "simulator",
      "group": "motif",
      "is_active": true
    },
    {
      "tag_id": "motif_undertale",
      "label": "undertale",
      "group": "motif",
      "is_active": true
    },
    {
      "tag_id": "motif_vtuber",
      "label": "個人Vtuber／しののめにこ",
      "group": "motif",
      "is_active": true
    },
    {
      "tag_id": "motif_vtuber_2",
      "label": "半セルフ受肉vtuberしののめにこ",
      "group": "motif",
      "is_active": true
    },
    {
      "tag_id": "motif_vtuber_3",
      "label": "個人勢Vtuberしののめにこ",
      "group": "motif",
      "is_active": true
    },
    {
      "tag_id": "motif_vtuber_4",
      "label": "vtuberしののめにこ",
      "group": "motif",
      "is_active": true
    },
    {
      "tag_id": "motif_vtuber_5",
      "label": "個人勢Vtuber／しののめにこ",
      "group": "motif",
      "is_active": true
    },
    {
      "tag_id": "tone_emotional",
      "label": "しんみり",
      "group": "tone",
      "is_active": true
    },
    {
      "tag_id": "tone_funny",
      "label": "笑い",
      "group": "tone",
      "is_active": true
    }
  ]
}
